{
    "<page title>": "New Panasonic Lumix DMC LF1 Digital Camera Black 12 1MP 885170123724 | eBay",
    "ac power adapter": "AC Adapter (Included)",
    "aspect ratio": "1:1, 3:2, 4:3, 16:9",
    "battery": "Rechargeable Lithium-Ion Battery Pack, 3.7VDC, 950mAh",
    "builtin memory": "87MB",
    "condition": "New: A brand-new, unused, unopened, undamaged item in its original packaging (where packaging is\napplicable). Packaging should be the same as what is found in a retail store, unless the item is handmade or was packaged by the manufacturer in non-retail packaging, such as an unprinted box or plastic bag. See the seller's listing for full details.\nSee all condition definitions- opens in a new window or tab\n... Read moreabout the condition",
    "dimensions wxhxd": "4.0 x 2.4 x 1.1\" / 10.2 x 6.1 x 2.8 cm",
    "file formats": "Still Images: JPEG, MPO, RAW\nMovies: MP4, MPEG-4 AVCHD\nAudio: AAC+, Dolby Digital 2ch",
    "focus range": "Wide: 19.69\" (50 cm) - Infinity\nTelephoto: 31.50\" (80 cm) - Infinity\nWide Macro: 1.18\" (3 cm) - Infinity\nTele Macro: 31.50\" (80 cm) - Infinity",
    "image stabilization": "Optical",
    "imaging": "Pixels Actual: 12.8 Megapixel\nEffective: 12.1 Megapixel Sensor 1/1.7\" MOS File FormatsStill Images: JPEG, MPO, RAW\nMovies: MP4, MPEG-4 AVCHD\nAudio: AAC+, Dolby Digital 2ch Max Resolution 12MP: 4000 x 3000 Aspect Ratio 1:1, 3:2, 4:3, 16:9 Image Stabilization Optical Optics Lens Leica DC Vario-Summicron, 10 elements in 8 groups\n4 Aspherical, 1 ED\nEFL: 6-42.8 mm (35 mm equivalent:28-200 mm)\nAperture: f/2 (W) - 5.9 (T) to f/8 Zoom Optical: 7.1x\nDigital: 4x\nIntelligent Zoom: 14.3x Focus Range Wide: 19.69\" (50 cm) - Infinity\nTelephoto: 31.50\" (80 cm) - Infinity\nWide Macro: 1.18\" (3 cm) - Infinity\nTele Macro: 31.50\" (80 cm) - Infinity Exposure Control ISO Sensitivity Auto, 80-6400 (Extended Mode: 12800-) Shutter 250 - 1/4000 seconds in Manual Mode Memory Built-in Memory 87MB Memory Card Type SD\nSDHC\nSDXC Power Battery Rechargeable Lithium-Ion Battery Pack, 3.7VDC, 950mAh AC Power Adapter AC Adapter (Included) Physical Dimensions (WxHxD) 4.0 x 2.4 x 1.1\" / 10.2 x 6.1 x 2.8 cm Weight 6.00 oz / 170 g without battery or card",
    "iso sensitivity": "Auto, 80-6400 (Extended Mode: 12800-)",
    "lens": "Leica DC Vario-Summicron, 10 elements in 8 groups\n4 Aspherical, 1 ED\nEFL: 6-42.8 mm (35 mm equivalent:28-200 mm)\nAperture: f/2 (W) - 5.9 (T) to f/8",
    "max resolution": "12MP: 4000 x 3000",
    "memory card type": "SD\nSDHC\nSDXC",
    "pixels": "Actual: 12.8 Megapixel\nEffective: 12.1 Megapixel",
    "sensor": "1/1.7\" MOS",
    "shutter": "250 - 1/4000 seconds in Manual Mode",
    "warranty": "1 Year Seller Warranty",
    "weight": "6.00 oz / 170 g without battery or card",
    "zoom": "Optical: 7.1x\nDigital: 4x\nIntelligent Zoom: 14.3x"
}