{
    "<page title>": "Casio Exilim 2 0 Mega Pixels Wearable Card Camera Collectors Find | eBay",
    "additional features": "Auto Power Save, DPOF Support, Date/Time Stamp, Not Interchangeable Lenses, PRINT Image Matching, USB",
    "battery form factor": "Manufacturer specific",
    "brand": "Casio",
    "camera flash features": "Auto Flash, Flash Off, Red-eye Reduction Flash",
    "camera type": "Point & Shoot",
    "connector types": "1 x DC power input, 1 x USB",
    "country/region of manufacture": "Japan",
    "depth": "0.44 in.",
    "description": "Excellent condition - works great! Great gift for any collector... Has original charging cradle, battery, memory card, carry strap. Great for vacations - Has record and play back ability! See all details below...\nDetailed item info\nProduct Information\nCasio EXILIM EX-S 2 is just perfect. Super thin and stylish, it is also incredibly functional. A high-resolution megapixel CCD provides 2.0 million effective pixels (2.11 million total pixels) for images that print beautifully. Fixed focus eliminates the need for lens movement, which shortens startup time and shooting time. Simply select the sample scene that matches the type of image you are trying to record and the camera performs troublesome setups automatically for beautiful pictures every time. DCF (Design rule for Camera File system) data storage protocol provides image intercompatibility between the digital camera and printers.\nProduct Identifiers\nBrand\nCasio\nModel\nS2\nMPN\nEXS2DBA\nUPC\n0079767682644, 079767682644, 4971850682646\nKey Features\nCamera Type\nPoint & Shoot\nDigital Zoom\n4x\nSensor Resolution\n2.0 MP\nScreen Size\n1.6\"\nOptical Sensor\nSensor Size\n1/1.8\"\nSensor Type\nCCD\nLens System\nFocus Adjustment\nFixed Focus, Focus Free\nFocal Length Equivalent to 35mm Camera\n36mm\nExposure\nMax Shutter Speed\n1/6400 sec\nMin Shutter Speed\n1/4 sec\nExposure compensation\n\u00b12 EV range, in 1/3 EV steps\nExposure Metering\nMatrix\nExposure Modes\nProgram\nCamera Flash\nFlash Type\nBuilt-in flash\nRed Eye Reduction\nYes\nEffective Flash Range\n1 m - 2 m\nCamera Flash Features\nAuto Flash, Flash Off, Red-eye Reduction Flash\nFlash Modes\nAuto Mode, Fill-in Mode, Flash ON Mode, OFF mode, Red-eye Reduction\nMemory / Storage\nIntegrated Memory size\n12 MB\nSupported Flash Memory\nBuilt-in, MultiMediaCard, SD Card, SD Memory Card\nViewfinder\nViewfinder Type\nOptical, Optical (Through-the-lens)\nOptical Viewfinder Type\nReal-image\nDimensions\nDepth\n0.44 in.\nHeight\n2.16 in.\nWidth\n3.46 in.\nWeight\n3.04 Oz.\nDisplay\nDisplay Type\nLCD\nDisplay Rotation\nBuilt-in\nScreen Details\nLCD display - TFT active matrix - 1.6\" - color\nDisplay Size\n1.6\"\nMicrophone\nMicrophone Type\nNone\nConnections\nConnector Types\n1 x DC power input, 1 x USB\nExpansion Slot\n1 x SD Memory Card\nSystem Requirements for PC Connection\nOperating System Supported\nApple Mac OS 7.6.x, Apple Mac OS 8.6 or later, Apple Mac OS 8.x, Apple Mac OS 9.0 or later, MS Windows 2000, MS Windows 98, MS Windows 98 SE, MS Windows ME, MS Windows XP, Microsoft Windows 2000, Microsoft Windows 98, Microsoft Windows ME, Microsoft Windows XP\nBattery\nBattery Form Factor\nManufacturer specific\nFile Format\nDigital Video Format\nAVI\nStill Image Format\nJPEG\nResolution\nMax Video Resolution\n320 x 240\nOther Features\nAdditional Features\nAuto Power Save, DPOF Support, Date/Time Stamp, Not Interchangeable Lenses, PRINT Image Matching, USB\nShooting Modes\nFrame Movie Mode\nMiscellaneous\nShooting Programs\nNight mode, Night scene, Portrait mode, Scenery, Twilight mode\nSpecial Effects\nBlack & White, Sepia\nWhite Balance\nAuto, Manual",
    "digital video format": "AVI",
    "digital zoom": "4x",
    "display rotation": "Built-in",
    "display size": "1.6\"",
    "display type": "LCD",
    "effective flash range": "1 m - 2 m",
    "expansion slot": "1 x SD Memory Card",
    "exposure compensation": "\u00b12 EV range, in 1/3 EV steps",
    "exposure metering": "Matrix",
    "exposure modes": "Program",
    "flash modes": "Auto Mode, Fill-in Mode, Flash ON Mode, OFF mode, Red-eye Reduction",
    "flash type": "Built-in flash",
    "focal length equivalent to 35mm camera": "36mm",
    "focus adjustment": "Fixed Focus, Focus Free",
    "height": "2.16 in.",
    "integrated memory size": "12 MB",
    "international buyers": "eBay Global Shipping Program",
    "max shutter speed": "1/6400 sec",
    "max video resolution": "320 x 240",
    "megapixels": "2.0 MP",
    "microphone type": "None",
    "min shutter speed": "1/4 sec",
    "model": "S2",
    "mpn": "EXS2DBA",
    "operating system supported": "Apple Mac OS 7.6.x, Apple Mac OS 8.6 or later, Apple Mac OS 8.x, Apple Mac OS 9.0 or later, MS Windows 2000, MS Windows 98, MS Windows 98 SE, MS Windows ME, MS Windows XP, Microsoft Windows 2000, Microsoft Windows 98, Microsoft Windows ME, Microsoft Windows XP",
    "optical viewfinder type": "Real-image",
    "red eye reduction": "Yes",
    "screen details": "LCD display - TFT active matrix - 1.6\" - color",
    "screen size": "1.6\"",
    "sensor resolution": "2.0 MP",
    "sensor size": "1/1.8\"",
    "sensor type": "CCD",
    "shooting modes": "Frame Movie Mode",
    "shooting programs": "Night mode, Night scene, Portrait mode, Scenery, Twilight mode",
    "special effects": "Black & White, Sepia",
    "still image format": "JPEG",
    "supported flash memory": "Built-in, MultiMediaCard, SD Card, SD Memory Card",
    "type": "Point & Shoot",
    "upc": "0079767682644, 079767682644, 4971850682646",
    "viewfinder type": "Optical, Optical (Through-the-lens)",
    "weight": "3.04 Oz.",
    "white balance": "Auto, Manual",
    "width": "3.46 in."
}