{
    "3d technology": "3D Not Supported",
    "<page title>": "Vizio E601I A3E 60 inch 1080p LED Smart HDTV Pick Up Only in North Las Vegas | eBay",
    "about the brand": "VIZIO is an American privately held electronics manufacturer established in 2002. Among its products are television sets, tablets and mobile phones, as VIZIO quickly became one of the most recognizable TV brands in North America. Nowadays, the company primarily produces television sets, as the first TV bearing the brand\u00e2\u0080\u0099s name, the P4 46\u00e2\u0080\u009d Plasma EDTV, was released in 2003. VIZIO became the largest LCD TV seller in North America for 2007 and since then focused on the LED-backlit LCD displays. The brand offers a diversity of TV models in a wide range of screen sizes, innovative designs and high-definition resolutions.",
    "additional features": "Built-in WiFi, DLNA Certified, Virtual Surrond, Internet Apps and Widgets",
    "aspect ratio": "14:9 Enhanced, 16:9",
    "audio type": "Virtual Surround",
    "battery type": "Alkaline",
    "brand": "Vizio",
    "builtin tuner": "ATSC",
    "contrast ratio": "1,000,000:1 dynamic contrast ratio",
    "definition": "HDTV",
    "depth": "1.94 in.",
    "description": "Combining a host of immersive features, the sleek Vizio 60-inch TV offers wholesome entertainment. With a 1080p HD resolution and 120 Hz refresh rate, this Vizio E601I-A3 lets you watch your favorite sporting events come alive. Moreover, with Vizio Internet Applications, you can instantly enjoy movies, TV shows and music on this LCD Internet TV. Equipped with Razor LED, the Vizio 60-inch TV renders images in rich colors and vivid detail. What\u00e2\u0080\u0099s more, with built-in Wi-Fi, this LCD Internet TV gives quick Internet access. What\u00e2\u0080\u0099s more, as this Vizio E601I-A3 has a QWERTY remote control, it facilitates ease of use.\nProduct Highlights Video User Manual About The BrandVIZIO is an American privately held electronics manufacturer established in 2002. Among its products are television sets, tablets and mobile phones, as VIZIO quickly became one of the most recognizable TV brands in North America. Nowadays, the company primarily produces television sets, as the first TV bearing the brand\u00e2\u0080\u0099s name, the P4 46\u00e2\u0080\u009d Plasma EDTV, was released in 2003. VIZIO became the largest LCD TV seller in North America for 2007 and since then focused on the LED-backlit LCD displays. The brand offers a diversity of TV models in a wide range of screen sizes, innovative designs and high-definition resolutions.\nProduct Identifiers BrandVizio ModelRazor E601I-A3 MPNE601I-A3\nKey Features TV TypeFlat-Panel Display TechnologyLED LCD Screen Size60\" DefinitionHDTV Aspect Ratio14:9 Enhanced, 16:9 Resolution1080p Display Resolution1920 x 1080 pixels 3D Technology3D Not Supported WiFi ConnectionBuilt-in WiFi Smart TV FeaturesDownloadable Apps, Internet Browsing, Smart Hub, Signature Services, Smart Content, ConnectShare, AllShare, Built-in Wi Fi\nTechnical Features Refresh Rate120 Hz Response Time4 ms Contrast Ratio1000000:1 Viewing Angle176\u00c2\u00b0 Built-in TunerATSC Supported Resolutions1080p (HDTV)\nPower On Mode Power90.8 W Sleep Mode Power1 W Energy StarEnergy Star Compliant\nConnectivity Front Input ConnectorsComponent x 1, HDMI x 2, USB Port\nAudio Features Number Of Speakers2 Speaker Power2 x 10 Watt Audio TypeVirtual Surround\nDimensions Height31.68 in. Width54.13 in. Depth1.94 in. Weight54.45 lbs\nMiscellaneous Room TypeCommercial Space, Large Hall, Living Room Remote Control Type (originally supplied by manufacturer)Standard Additional FeaturesBuilt-in WiFi, DLNA Certified, Internet Apps and Widgets, Virtual Surrond",
    "display resolution": "1920 x 1080 pixels",
    "display technology": "LED LCD",
    "energy star": "Energy Star Compliant",
    "front input connectors": "Component x 1, HDMI x 2, USB Port",
    "height": "31.68 in.",
    "max resolution": "1080p",
    "model": "Razor E601I-A3",
    "model no": "E601I-A3E",
    "mpn": "E601I-A3",
    "multi pack indicator": "No",
    "number of speakers": "2",
    "on mode power": "90.8 W",
    "primary color": "Black",
    "product in inches l x w x h": "57.93 x 6.65 x 35.71",
    "refresh rate": "120 Hz",
    "remote control type originally supplied by manufacturer": "Standard",
    "resolution": "1080p",
    "response time": "4ms",
    "room type": "Commercial Space, Large Hall, Living Room",
    "screen size": "60\"",
    "shipping weight in pounds": "61.73",
    "sleep mode power": "1 W",
    "smart tv features": "Downloadable Apps, Internet Browsing, Smart Hub, Signature Services, Smart Content, ConnectShare, AllShare, Built-in Wi Fi",
    "speaker power": "2 x 10 Watt",
    "supported resolutions": "1080p (HDTV)",
    "tv type": "Flat-Panel",
    "video": "Class Size: 60\"\nScreen Size (Diag.): 60.04\u00e2\u0080\u009d\nBacklight Type: Razor LED\u00e2\u0084\u00a2\n3D: N/A\nResolution: 1920 x 1080 (1080p)\nColors: 1.07 Billion (10-bits)\nDynamic Contrast Ratio: 1,000,000:1\nRefresh Rate: 120Hz Refresh Rate with smooth motion\nResponse Time: 4ms\nViewable Angle (H/V): 176 /176\nOSD Language: English, Spanish, FrenchAudioSRS StudioSound\u00e2\u0084\u00a2: Yes\nSRS TruVolume\u00e2\u0084\u00a2: Yes\nSpeakers/Power Output: 2 x 10WInputsHDMI: 2 (side), 2 (down)\nComponent: 1 (side)\nComposite: 1 (shared with component)\nPC: 1 VGA (down)\nRF Connector for Internal Tuner: 1 (down)\nEthernet: 1 (down)\nUSB 2.0: 2 (side)OutputsDigital Audio Out (SPDIF): 1 (down)\nAnalog Audio Out: 1 RCA (down)Multimedia SupportMusic: Yes\nPhoto: Yes\nVideo: Yes\nAdditional FeaturesVIA (VIZIO Internet Apps): Yes\n3D File Formats Supported: N/A\nSmart Dimming: No\nSmooth Motion: Yes\nAmbient Light Sensor: Yes\nWiFi: 802.11n single band\nBluetooth: N/A\nHDMI CEC: Yes\nHDMI ARC: Yes\nPIP (Picture in Picture): No\nMercury Free: Yes\n3D Glasses: N/A\nCertifications: UL, CUL, FCC Class B, HDMI 1.4 incl. CEC/ARC, Vizio AQ, Vizio PQ, Dolby Digital Plus\nCompliance: ENERGY STAR\u00c2\u00ae 6.0, ATSC Spec A/65, EIA/CEA-766-A, California Energy Commission Auto Shut DownWall Mount SpecificationsHole Pattern: 400mm x 400mm\nScrew Size: M6\nScrew Length: 10mm\nScrew Pitch: 1mmPower RatingsPower Consumption: 90.8W\nStandby Power Consumption: <1W\nEnergy Compliance: ENERGY STAR \u00c2\u00ae 6.0Product DimensionsWith Stand Inches: 54.13\u00e2\u0080\u009dW x 33.51\u00e2\u0080\u009dH x 11.02\u00e2\u0080\u009dD\nProduct Weight With Stand: 61.73 lbs\nWithout Stand Inches: 54.13\u00e2\u0080\u009dW x 31.68\u00e2\u0080\u009dH x 1.94\u00e2\u0080\u009dD\nProduct Weight Without Stand: 54.45 lbsPackaging DimensionsInches: 57.83\u00e2\u0080\u009dW x 35.71\u00e2\u0080\u009dH x 6.65\u00e2\u0080\u009dD\nProduct Weight With Box: 72.75 lbs",
    "viewing angle": "176\u00c2\u00b0",
    "weight": "54.45 lbs",
    "width": "54.13 in.",
    "wifi connection": "Built-in WiFi"
}