{
    "3d technology": "3D Not Supported",
    "<page title>": "Samsung UN32EH5000 32\" 1080p 60Hz LED HDTV 036725236615 | eBay",
    "about the brand": "Samsung is the biggest South Korean multinational conglomerate company, which comprises numerous subsidiaries including Samsung Electronics \u00e2\u0080\u0093 the world\u00e2\u0080\u0099s largest company serving the IT sector. Among the branded products are computers, mobile phones, digital televisions and liquid crystal displays, all which are worldwide recognizable for their reliability, fine craftsmanship, high-quality and innovative technologies. The company attained first place for LCD market share six years in a row, and is noted for developing the world\u00e2\u0080\u0099s first real double-sided LCD screen as well.",
    "additional features": "Closed Captioning, Clock & On/Off Timer, Game Mode, Eco Sensor, Auto Power Off",
    "aspect ratio": "14:9 Enhanced, 16:9",
    "audio type": "Stereo",
    "brand": "Samsung",
    "builtin tuner": "ATSC, QAM",
    "condition": "New: A brand-new, unused, unopened, undamaged item in its original packaging (where packaging is\napplicable). Packaging should be the same as what is found in a retail store, unless the item is handmade or was packaged by the manufacturer in non-retail packaging, such as an unprinted box or plastic bag. See the seller's listing for full details.\nSee all condition definitions- opens in a new window or tab\n... Read moreabout the condition",
    "definition": "HDTV",
    "depth": "6.4 in.",
    "description": "With a design that is conducive to small spaces and technology that provides a large, clear picture quality, the Samsung 32-inch TV is designed to be used in a variety of rooms while providing high-level image clarity. The Samsung UN32EH5000F is a screen designed with dimensions of 29.1 inches wide, 17.5 inches tall, and just 3.7 inches deep. This LCD TV weighs just 13 lbs and can be easily set up in almost any room. As a screen that is ENERGY STAR efficient and consumers only 0.3 watts on standby and 33 watts in normal operation, the Samsung 32-inch TV is slim not only in physical dimensions, but power consumption as well. The Samsung UN32EH5000F is designed to provide a native resolution of 1920x1080 with a dynamic contrast ratio of 3500000:1 and a clear motion rate of 120. This LCD TV offers a variety of features such as wide color enhancement, ConnectShare, game mode, and even an eco sensor. The Samsung 32-inch TV is a nice screen option for home use.\nProduct Highlights Video About The BrandSamsung is the biggest South Korean multinational conglomerate company, which comprises numerous subsidiaries including Samsung Electronics \u00e2\u0080\u0093 the world\u00e2\u0080\u0099s largest company serving the IT sector. Among the branded products are computers, mobile phones, digital televisions and liquid crystal displays, all which are worldwide recognizable for their reliability, fine craftsmanship, high-quality and innovative technologies. The company attained first place for LCD market share six years in a row, and is noted for developing the world\u00e2\u0080\u0099s first real double-sided LCD screen as well.\nProduct Identifiers BrandSamsung Family Line5000 Series ModelUN32EH5000 MPNUN32EH5000FXZA UPC036725236615\nKey Features TV TypeFlat-Panel Display TechnologySlim LED Screen Size32\" DefinitionHDTV Aspect Ratio14:9 Enhanced, 16:9 Resolution1080p Display Resolution1920 x 1080 pixels 3D Technology3D Not Supported Smart TV FeaturesNot Supported\nTechnical Features Built-in TunerATSC, QAM\nPower On Mode Power33 W Sleep Mode Power0.2 W\nAudio Features Number Of Speakers2 Audio TypeStereo\nDimensions Height20.9 in. Width35.5 in. Depth6.4 in. Weight13 lbs\nMiscellaneous Exterior ColorBlack Additional FeaturesAuto Power Off, Clock & On/Off Timer, Closed Captioning, Eco Sensor, Game Mode",
    "display resolution": "1920 x 1080 pixels",
    "display technology": "Slim LED",
    "exterior color": "Black",
    "family line": "5000 Series",
    "height": "20.9 in.",
    "max. resolution": "1080p",
    "model": "UN32EH5000",
    "mpn": "UN32EH5000FXZA",
    "number of speakers": "2",
    "on mode power": "33 W",
    "resolution": "1080p",
    "screen size": "32\"",
    "sleep mode power": "0.2 W",
    "smart tv features": "Not Supported",
    "tv type": "Flat-Panel",
    "upc": "036725236615",
    "weight": "13 lbs",
    "width": "35.5 in."
}