{
    "3d technology": "3D Not Supported",
    "<page title>": "Dynex DX LCD19 09 19\" HD LCD Television 1440 x 900 720P 16 10 300 Nits 600603115974 | eBay",
    "about the brand": "Dynex is an exclusive brand of Best Buy Co., Inc.\u00c2 It is an American\u00c2 consumer electronics company, headquartered in\u00c2 Richfield, which operates not only in the United States, but also in Mexico, Puerto Rico, Canada, and China. The corporation was launched by\u00c2 Richard M. Schulze\u00c2 and Gary Smoliak in 1966 as an audio specialty store. It was renamed and rebranded with more emphasis placed on consumer electronics in 1983. Currently the Dynex products include advanced office equipment, computers, televisions, various accessories, and mobile phones.",
    "additional features": "Headphone Jack",
    "aspect ratio": "16:10",
    "audio type": "Stereo",
    "brand": "Dynex",
    "brightness": "300 cd/m\u00c2\u00b2\u00c2\u00b0",
    "channel labels": "With Channel Labels",
    "comb filter": "3DYC / 3D Digital",
    "contrast ratio": "800:1",
    "definition": "HDTV-Ready",
    "depth": "4.6 in.",
    "description": "this brilliant 19\" widescreen LCD HDTV. It supports 720p high-definition resolution and features a PC input that lets you turn this compact TV into a monitor for your computer.\nProduct Highlights About The BrandDynex is an exclusive brand of Best Buy Co., Inc.\u00c2 It is an American\u00c2 consumer electronics company, headquartered in\u00c2 Richfield, which operates not only in the United States, but also in Mexico, Puerto Rico, Canada, and China. The corporation was launched by\u00c2 Richard M. Schulze\u00c2 and Gary Smoliak in 1966 as an audio specialty store. It was renamed and rebranded with more emphasis placed on consumer electronics in 1983. Currently the Dynex products include advanced office equipment, computers, televisions, various accessories, and mobile phones.\nProduct Identifiers BrandDynex ModelDX-LCD19-09 MPNDX-LCD19-09 UPC600603115974\nKey Features TV TypeFlat-Panel Display TechnologyLCD Screen Size19\" DefinitionHDTV-Ready Aspect Ratio16:10 Resolution720p Display Resolution1440 x 900 pixels 3D Technology3D Not Supported Smart TV FeaturesNot Supported\nTechnical Features Refresh Rate60 Hz Response Time5 ms Contrast Ratio800:1 Viewing Angle160\u00c2\u00b0 Supported Resolutions720p (HDTV) Comb Filter3DYC / 3D Digital Brightness300 cd/m\u00c2\u00b2\u00c2\u00b0\nPower On Mode Power43 W Energy StarEnergy Star Compliant\nAudio Features Number Of Speakers2 Speaker Power2 x 3 Watt Audio TypeStereo\nDimensions Height8.2 in. Width17.6 in. Depth4.6 in. Weight7.3 lbs\nMiscellaneous OSD LanguagesEnglish, French, Spanish Channel LabelsWith Channel Labels Parental ControlV-Chip Sleep TimerWith Sleep Timer Room TypeBedroom, Children's Bedroom Remote Control Type (originally supplied by manufacturer)Standard Exterior ColorBlack Additional FeaturesHeadphone Jack",
    "display resolution": "1440 x 900 pixels",
    "display technology": "LCD",
    "energy star": "Energy Star Compliant",
    "exterior color": "Black",
    "height": "8.2 in.",
    "max resolution": "720p",
    "model": "DX-LCD19-09",
    "mpn": "DX-LCD19-09",
    "number of speakers": "2",
    "on mode power": "43 W",
    "osd languages": "English, French, Spanish",
    "parental control": "V-Chip",
    "refresh rate": "60 Hz",
    "remote control type originally supplied by manufacturer": "Standard",
    "resolution": "720p",
    "response time": "5 ms",
    "room type": "Bedroom, Children's Bedroom",
    "screen size": "19\"",
    "sleep timer": "With Sleep Timer",
    "smart tv features": "Not Supported",
    "speaker power": "2 x 3 Watt",
    "supported resolutions": "720p (HDTV)",
    "tv type": "Flat-Panel",
    "upc": "600603115974",
    "ups and usps": "Any orders of $250.00 or more will be shipped with Signature Required. Please make sure you are available to sign for these orders.",
    "viewing angle": "160\u00c2\u00b0",
    "weight": "7.3 lbs",
    "width": "17.6 in."
}